kan/KANLayer.py
kan/LBFGS.py
kan/MLP.py
kan/MultKAN.py
kan/Symbolic_KANLayer.py
kan/__init__.py
kan/compiler.py
kan/experiment.py
kan/feynman.py
kan/hypothesis.py
kan/spline.py
kan/train_eval_utils.py
kan/utils.py
ymskan-0.0.41.dist-info/licenses/LICENSE
ymskan-0.0.41.dist-info/METADATA
ymskan-0.0.41.dist-info/WHEEL
ymskan-0.0.41.dist-info/top_level.txt
ymskan-0.0.41.dist-info/RECORD
