Metadata-Version: 2.4
Name: ymskan
Version: 0.0.41
Summary: works
Author: yms
Author-email: 226000@qq.com
Requires-Python: >=3.6
License-File: LICENSE
Dynamic: author
Dynamic: author-email
Dynamic: description
Dynamic: description-content-type
Dynamic: license-file
Dynamic: requires-python
Dynamic: summary
